oprel/__init__.py
oprel/api_models.py
oprel/client_api.py
oprel/version.py
oprel/cli/__init__.py
oprel/cli/main.py
oprel/client/__init__.py
oprel/client/base.py
oprel/client/http.py
oprel/client/pipe.py
oprel/client/socket.py
oprel/core/__init__.py
oprel/core/config.py
oprel/core/exceptions.py
oprel/core/model.py
oprel/downloader/__init__.py
oprel/downloader/aliases.py
oprel/downloader/cache.py
oprel/downloader/hub.py
oprel/downloader/verification.py
oprel/runtime/__init__.py
oprel/runtime/monitor.py
oprel/runtime/process.py
oprel/runtime/backends/__init__.py
oprel/runtime/backends/base.py
oprel/runtime/backends/exllama.py
oprel/runtime/backends/llama_cpp.py
oprel/runtime/backends/vllm.py
oprel/runtime/binaries/__init__.py
oprel/runtime/binaries/installer.py
oprel/runtime/binaries/registry.py
oprel/runtime/binaries/validator.py
oprel/server/__init__.py
oprel/server/daemon.py
oprel/telemetry/__init__.py
oprel/telemetry/benchmarks.py
oprel/telemetry/hardware.py
oprel/telemetry/recommender.py
oprel/utils/__init__.py
oprel/utils/chat_templates.py
oprel/utils/logging.py
oprel/utils/model_info.py
oprel/utils/paths.py
oprel/utils/platform.py
oprel-0.2.2.dist-info/licenses/LICENSE
oprel-0.2.2.dist-info/METADATA
oprel-0.2.2.dist-info/WHEEL
oprel-0.2.2.dist-info/entry_points.txt
oprel-0.2.2.dist-info/top_level.txt
oprel-0.2.2.dist-info/RECORD
