Metadata-Version: 2.4
Name: oprel
Version: 0.2.2
Summary: Run LLMs locally with one line of Python. Ollama alternative with server mode, conversation memory, and 50+ model aliases. The SQLite of AI.
Home-page: https://github.com/ragultv/oprel-SDK
Author: Ragul
Author-email: Ragul <tragulragul@gmail.com>
License: MIT
Project-URL: Homepage, https://github.com/ragultv/oprel-SDK
Project-URL: Documentation, https://github.com/ragultv/oprel-SDK#readme
Project-URL: Repository, https://github.com/ragultv/oprel-SDK
Project-URL: Issues, https://github.com/ragultv/oprel-SDK/issues
Keywords: llm,local-llm,local-ai,inference,llm-inference,ollama,ollama-alternative,ollama-python,gguf,llama-cpp,llama.cpp,quantization,llama,llama3,mistral,gemma,qwen,phi,deepseek,chatbot,text-generation,ai-chat,conversational-ai,offline-ai,cpu-inference,gpu-inference,model-server,ai-runtime,machine-learning,privacy,on-premise,edge-ai,embedded-ai
Classifier: Development Status :: 4 - Beta
Classifier: Intended Audience :: Developers
Classifier: Intended Audience :: Science/Research
Classifier: Intended Audience :: Information Technology
Classifier: License :: OSI Approved :: MIT License
Classifier: Operating System :: OS Independent
Classifier: Operating System :: MacOS
Classifier: Operating System :: Microsoft :: Windows
Classifier: Operating System :: POSIX :: Linux
Classifier: Programming Language :: Python :: 3
Classifier: Programming Language :: Python :: 3.9
Classifier: Programming Language :: Python :: 3.10
Classifier: Programming Language :: Python :: 3.11
Classifier: Programming Language :: Python :: 3.12
Classifier: Programming Language :: Python :: 3.13
Classifier: Topic :: Scientific/Engineering :: Artificial Intelligence
Classifier: Topic :: Software Development :: Libraries :: Python Modules
Classifier: Topic :: Text Processing :: Linguistic
Classifier: Typing :: Typed
Classifier: Environment :: Console
Classifier: Environment :: GPU
Classifier: Natural Language :: English
Requires-Python: >=3.9
License-File: LICENSE
Requires-Dist: huggingface-hub>=0.20.0
Requires-Dist: psutil>=5.9.0
Requires-Dist: requests>=2.31.0
Requires-Dist: pydantic>=2.0.0
Requires-Dist: rich>=13.0.0
Provides-Extra: local
Requires-Dist: torch>=2.1.0; extra == "local"
Provides-Extra: cuda
Requires-Dist: torch>=2.1.0; extra == "cuda"
Provides-Extra: server
Requires-Dist: fastapi>=0.109.0; extra == "server"
Requires-Dist: uvicorn>=0.27.0; extra == "server"
Provides-Extra: dev
Requires-Dist: pytest>=7.4.0; extra == "dev"
Requires-Dist: pytest-asyncio>=0.21.0; extra == "dev"
Requires-Dist: pytest-cov>=4.1.0; extra == "dev"
Requires-Dist: black>=23.0.0; extra == "dev"
Requires-Dist: ruff>=0.1.0; extra == "dev"
Requires-Dist: mypy>=1.7.0; extra == "dev"
Requires-Dist: pre-commit>=3.5.0; extra == "dev"
Provides-Extra: docs
Requires-Dist: mkdocs>=1.5.0; extra == "docs"
Requires-Dist: mkdocs-material>=9.4.0; extra == "docs"
Provides-Extra: all
Requires-Dist: oprel[cuda,dev,docs,local,server]; extra == "all"
Dynamic: author
Dynamic: home-page
Dynamic: license-file
Dynamic: requires-python
